Workbook
Name Slicer_Customer_Location: #N/A
Name Slicer_Date: #N/A
Name Slicer_Payment_Method1: #N/A
Name Slicer_Status1: #N/A

Sheet Vlookup
A1: OrderID | B1: sales | C1: payment mode | D1: price
A2: ORD0002 | B2: =VLOOKUP(A2,Amazon_sales!$A$1:$G$250,7,0) -> 270000 | C2: =VLOOKUP(A2,Table1[[#All],[Order ID]:[Payment Method]],10,0) -> Debit Card | D2: =VLOOKUP(A2,Amazon_sales!$A$1:$G$250,5,0) -> 5000
A3: ORD0003 | B3: =VLOOKUP(A3,Amazon_sales!$A$1:$G$250,7,0) -> 112000 | C3: =VLOOKUP(A3,Table1[[#All],[Order ID]:[Payment Method]],10,0) -> Amazon Pay | D3: =VLOOKUP(A3,Amazon_sales!$A$1:$G$250,5,0) -> 2000
A4: ORD0004 | B4: =VLOOKUP(A4,Amazon_sales!$A$1:$G$250,7,0) -> 144000 | C4: =VLOOKUP(A4,Table1[[#All],[Order ID]:[Payment Method]],10,0) -> Credit Card | D4: =VLOOKUP(A4,Amazon_sales!$A$1:$G$250,5,0) -> 2000
A5: ORD0005 | B5: =VLOOKUP(A5,Amazon_sales!$A$1:$G$250,7,0) -> 12000 | C5: =VLOOKUP(A5,Table1[[#All],[Order ID]:[Payment Method]],10,0) -> Debit Card | D5: =VLOOKUP(A5,Amazon_sales!$A$1:$G$250,5,0) -> 1000
A6: ORD0006 | B6: =VLOOKUP(A6,Amazon_sales!$A$1:$G$250,7,0) -> 22500 | C6: =VLOOKUP(A6,Table1[[#All],[Order ID]:[Payment Method]],10,0) -> Credit Card | D6: =VLOOKUP(A6,Amazon_sales!$A$1:$G$250,5,0) -> 500
A7: ORD0007 | B7: =VLOOKUP(A7,Amazon_sales!$A$1:$G$250,7,0) -> 134000 | C7: =VLOOKUP(A7,Table1[[#All],[Order ID]:[Payment Method]],10,0) -> PayPal | D7: =VLOOKUP(A7,Amazon_sales!$A$1:$G$250,5,0) -> 2000
A8: ORD0008 | B8: =VLOOKUP(A8,Amazon_sales!$A$1:$G$250,7,0) -> 69000 | C8: =VLOOKUP(A8,Table1[[#All],[Order ID]:[Payment Method]],10,0) -> PayPal | D8: =VLOOKUP(A8,Amazon_sales!$A$1:$G$250,5,0) -> 3000
A9: ORD0009 | B9: =VLOOKUP(A9,Amazon_sales!$A$1:$G$250,7,0) -> 445000 | C9: =VLOOKUP(A9,Table1[[#All],[Order ID]:[Payment Method]],10,0) -> PayPal | D9: =VLOOKUP(A9,Amazon_sales!$A$1:$G$250,5,0) -> 5000
A10: ORD0010 | B10: =VLOOKUP(A10,Amazon_sales!$A$1:$G$250,7,0) -> 84000 | C10: =VLOOKUP(A10,Table1[[#All],[Order ID]:[Payment Method]],10,0) -> Credit Card | D10: =VLOOKUP(A10,Amazon_sales!$A$1:$G$250,5,0) -> 2000
A11: ORD0011 | B11: =VLOOKUP(A11,Amazon_sales!$A$1:$G$250,7,0) -> 102000 | C11: =VLOOKUP(A11,Table1[[#All],[Order ID]:[Payment Method]],10,0) -> Amazon Pay | D11: =VLOOKUP(A11,Amazon_sales!$A$1:$G$250,5,0) -> 2000
A12: ORD0012 | B12: =VLOOKUP(A12,Amazon_sales!$A$1:$G$250,7,0) -> 45000 | C12: =VLOOKUP(A12,Table1[[#All],[Order ID]:[Payment Method]],10,0) -> Credit Card | D12: =VLOOKUP(A12,Amazon_sales!$A$1:$G$250,5,0) -> 1000
A13: ORD0013 | B13: =VLOOKUP(A13,Amazon_sales!$A$1:$G$250,7,0) -> 31500 | C13: =VLOOKUP(A13,Table1[[#All],[Order ID]:[Payment Method]],10,0) -> Gift Card | D13: =VLOOKUP(A13,Amazon_sales!$A$1:$G$250,5,0) -> 500

Sheet Xlookup
A1: OrderID | B1: date
A2: ORD0002 | B2: =_xlfn.XLOOKUP(A2,Amazon_sales!$A:$A,Amazon_sales!$B:$B,"Not found",0) -> 45736
A3: ORD0003 | B3: =_xlfn.XLOOKUP(A3,Amazon_sales!$A:$A,Amazon_sales!$B:$B,"Not found",0) -> 45703
A4: ORD0004 | B4: =_xlfn.XLOOKUP(A4,Amazon_sales!$A:$A,Amazon_sales!$B:$B,"Not found",0) -> 45707
A5: ORD0005 | B5: =_xlfn.XLOOKUP(A5,Amazon_sales!$A:$A,Amazon_sales!$B:$B,"Not found",0) -> 45726
A6: ORD0006 | B6: =_xlfn.XLOOKUP(A6,Amazon_sales!$A:$A,Amazon_sales!$B:$B,"Not found",0) -> 45736
A7: ORD0007 | B7: =_xlfn.XLOOKUP(A7,Amazon_sales!$A:$A,Amazon_sales!$B:$B,"Not found",0) -> 45734
A8: ORD0008 | B8: =_xlfn.XLOOKUP(A8,Amazon_sales!$A:$A,Amazon_sales!$B:$B,"Not found",0) -> 45718
A9: ORD0009 | B9: =_xlfn.XLOOKUP(A9,Amazon_sales!$A:$A,Amazon_sales!$B:$B,"Not found",0) -> 45724
A10: ORD0010 | B10: =_xlfn.XLOOKUP(A10,Amazon_sales!$A:$A,Amazon_sales!$B:$B,"Not found",0) -> 45728
A11: ORD0011 | B11: =_xlfn.XLOOKUP(A11,Amazon_sales!$A:$A,Amazon_sales!$B:$B,"Not found",0) -> 45705
A12: ORD0012 | B12: =_xlfn.XLOOKUP(A12,Amazon_sales!$A:$A,Amazon_sales!$B:$B,"Not found",0) -> 45729
A13: ORD0013 | B13: =_xlfn.XLOOKUP(A13,Amazon_sales!$A:$A,Amazon_sales!$B:$B,"Not found",0) -> 45717

Sheet Sheet4
A3: Sum of Price | B3: Column Labels
A4: Row Labels | B4: Books | C4: Clothing | D4: Electronics | E4: Footwear | F4: Home Appliances | G4: Grand Total
A5: Book | B5: 60500 | G5: 60500 | O5: Row Labels | P5: Sum of Quantity | Q5: Sum of Price
A6: Headphones | D6: 51500 | G6: 51500 | K6: Row Labels | L6: Sum of profit | O6: Book | P6: 916 | Q6: 60500
A7: Jeans | C7: 44392 | G7: 44392 | K7: Book | L7: 133355000 | O7: Headphones | P7: 1064 | Q7: 51500
A8: Laptop | D8: 51392 | G8: 51392 | K8: Headphones | L8: 134287000 | O8: Jeans | P8: 909 | Q8: 44392
A9: Refrigerator | F9: 54700 | G9: 54700 | K9: Jeans | L9: 114111092 | O9: Laptop | P9: 671 | Q9: 51392
A10: Running Shoes | E10: 76784 | G10: 76784 | K10: Laptop | L10: 53042888 | O10: Refrigerator | P10: 991 | Q10: 54700
A11: Smartphone | D11: 80446 | G11: 80446 | K11: Refrigerator | L11: 120313300 | O11: Running Shoes | P11: 1243 | Q11: 76784
A12: Smartwatch | D12: 72892 | G12: 72892 | K12: Running Shoes | L12: 186561668 | O12: Smartphone | P12: 1233 | Q12: 80446
A13: T-Shirt | C13: 36400 | G13: 36400 | K13: Smartphone | L13: 127556236 | O13: Smartwatch | P13: 1285 | Q13: 72892
A14: Washing Machine | F14: 27700 | G14: 27700 | K14: Smartwatch | L14: 153402528 | O14: T-Shirt | P14: 920 | Q14: 36400
A15: Grand Total | B15: 60500 | C15: 80792 | D15: 256230 | E15: 76784 | F15: 82400 | G15: 556706 | K15: T-Shirt | L15: 107102400 | O15: Washing Machine | P15: 639 | Q15: 27700
K16: Washing Machine | L16: 41582300 | O16: Grand Total | P16: 9871 | Q16: 556706
K17: Grand Total | L17: 1171314412
B19: Sum of Total Sales | C19: Column Labels
B20: Row Labels | C20: Completed | D20: Pending | E20: Grand Total
B21: Amazon Pay | C21: 1043484 | D21: 2579068 | E21: 3622552
B22: Credit Card | C22: 1828000 | D22: 2477900 | E22: 4305900
B23: Debit Card | C23: 1626500 | D23: 2192176 | E23: 3818676
B24: Gift Card | C24: 1238400 | D24: 2256500 | E24: 3494900
B25: PayPal | C25: 4698016 | D25: 1664400 | E25: 6362416
B26: Grand Total | C26: 10434400 | D26: 11170044 | E26: 21604444

Sheet Amazon_sales
A1: Order ID | B1: Date | C1: Product | D1: Category | E1: Price | F1: Quantity | G1: Total Sales | H1: Customer Name | I1: Customer Location | J1: Payment Method | K1: Status | L1: profit | N1: high sales/low sales | O1: order month-year | P1: high/med/low profit | Q1: paid/not paid
A2: ORD0001 | B2: 45730 | C2: Running Shoes | D2: Footwear | E2: 3000 | F2: 33 | G2: =Table1[[#This Row],[Price]]*Table1[[#This Row],[Quantity]] -> 99000 | H2: Emma Clark | I2: New York | J2: Debit Card | K2: Completed | L2: =Table1[[#This Row],[Total Sales]]*Table1[[#This Row],[Quantity]] -> 3267000 | N2: =IF(AND(Table1[[#This Row],[Price]]>50,Table1[[#This Row],[Category]]="Footwear"),"High","Low") -> High | O2: =TEXT(Table1[[#This Row],[Date]],"MMM-YY") -> Mar-25 | P2: =IF(Table1[[#This Row],[profit]]>5000000,"High",IF(Table1[[#This Row],[profit]]>3000000,"Medium","Low")) -> Medium | Q2: =IF(Table1[[#This Row],[Status]]="Completed","Paid","Not Paid") -> Paid | U2: show me the total sales where category is footwear | V2: =SUMIF($D:$D,"Footwear",$G:$G) -> 3420156
A3: ORD0002 | B3: 45736 | C3: Headphones | D3: Electronics | E3: 5000 | F3: 54 | G3: =Table1[[#This Row],[Price]]*Table1[[#This Row],[Quantity]] -> 270000 | H3: Emily Johnson | I3: San Francisco | J3: Debit Card | K3: Pending | L3: =Table1[[#This Row],[Total Sales]]*Table1[[#This Row],[Quantity]] -> 14580000 | N3: =IF(AND(Table1[[#This Row],[Price]]>50,Table1[[#This Row],[Category]]="Footwear"),"High","Low") -> Low | O3: =TEXT(Table1[[#This Row],[Date]],"MMM-YY") -> Mar-25 | P3: =IF(Table1[[#This Row],[profit]]>5000000,"High",IF(Table1[[#This Row],[profit]]>3000000,"Medium","Low")) -> High | Q3: =IF(Table1[[#This Row],[Status]]="Completed","Paid","Notpaid") -> Notpaid | U3: show me the total Profit where location is new york | V3: =SUMIF($I:$I,"New York",$L:$L) -> 53137528
A4: ORD0003 | B4: 45703 | C4: Running Shoes | D4: Footwear | E4: 2000 | F4: 56 | G4: =Table1[[#This Row],[Price]]*Table1[[#This Row],[Quantity]] -> 112000 | H4: John Doe | I4: Denver | J4: Amazon Pay | K4: Completed | L4: =Table1[[#This Row],[Total Sales]]*Table1[[#This Row],[Quantity]] -> 6272000 | N4: =IF(AND(Table1[[#This Row],[Price]]>50,Table1[[#This Row],[Category]]="Footwear"),"High","Low") -> High | O4: =TEXT(Table1[[#This Row],[Date]],"MMM-YY") -> Feb-25 | P4: =IF(Table1[[#This Row],[profit]]>5000000,"High",IF(Table1[[#This Row],[profit]]>3000000,"Medium","Low")) -> High | Q4: =IF(Table1[[#This Row],[Status]]="Completed","Paid","Notpaid") -> Paid
A5: ORD0004 | B5: 45707 | C5: Running Shoes | D5: Footwear | E5: 2000 | F5: 72 | G5: =Table1[[#This Row],[Price]]*Table1[[#This Row],[Quantity]] -> 144000 | H5: Olivia Wilson | I5: Dallas | J5: Credit Card | K5: Pending | L5: =Table1[[#This Row],[Total Sales]]*Table1[[#This Row],[Quantity]] -> 10368000 | N5: =IF(AND(Table1[[#This Row],[Price]]>50,Table1[[#This Row],[Category]]="Footwear"),"High","Low") -> High | O5: =TEXT(Table1[[#This Row],[Date]],"MMM-YY") -> Feb-25 | P5: =IF(Table1[[#This Row],[profit]]>5000000,"High",IF(Table1[[#This Row],[profit]]>3000000,"Medium","Low")) -> High | Q5: =IF(Table1[[#This Row],[Status]]="Completed","Paid","Notpaid") -> Notpaid
A6: ORD0005 | B6: 45726 | C6: Smartwatch | D6: Electronics | E6: 1000 | F6: 12 | G6: =Table1[[#This Row],[Price]]*Table1[[#This Row],[Quantity]] -> 12000 | H6: Emma Clark | I6: New York | J6: Debit Card | K6: Pending | L6: =Table1[[#This Row],[Total Sales]]*Table1[[#This Row],[Quantity]] -> 144000 | N6: =IF(AND(Table1[[#This Row],[Price]]>50,Table1[[#This Row],[Category]]="Footwear"),"High","Low") -> Low | O6: =TEXT(Table1[[#This Row],[Date]],"MMM-YY") -> Mar-25 | P6: =IF(Table1[[#This Row],[profit]]>5000000,"High",IF(Table1[[#This Row],[profit]]>3000000,"Medium","Low")) -> Low | Q6: =IF(Table1[[#This Row],[Status]]="Completed","Paid","Notpaid") -> Notpaid
A7: ORD0006 | B7: =_xlfn.XLOOKUP(A7,Amazon_sales!$A:$A,Amazon_sales!$B:$B,"Not found",0) -> 45736 | C7: T-Shirt | D7: Clothing | E7: 500 | F7: 45 | G7: =Table1[[#This Row],[Price]]*Table1[[#This Row],[Quantity]] -> 22500 | H7: John Doe | I7: Dallas | J7: Credit Card | K7: Pending | L7: =Table1[[#This Row],[Total Sales]]*Table1[[#This Row],[Quantity]] -> 1012500 | N7: =IF(AND(Table1[[#This Row],[Price]]>50,Table1[[#This Row],[Category]]="Footwear"),"High","Low") -> Low | O7: =TEXT(Table1[[#This Row],[Date]],"MMM-YY") -> Jan-00 | P7: =IF(Table1[[#This Row],[profit]]>5000000,"High",IF(Table1[[#This Row],[profit]]>3000000,"Medium","Low")) -> Low | Q7: =IF(Table1[[#This Row],[Status]]="Completed","Paid","Notpaid") -> Notpaid
A8: ORD0007 | B8: 45734 | C8: Smartwatch | D8: Electronics | E8: 2000 | F8: 67 | G8: =Table1[[#This Row],[Price]]*Table1[[#This Row],[Quantity]] -> 134000 | H8: Emma Clark | I8: Houston | J8: PayPal | K8: Completed | L8: =Table1[[#This Row],[Total Sales]]*Table1[[#This Row],[Quantity]] -> 8978000 | N8: =IF(AND(Table1[[#This Row],[Price]]>50,Table1[[#This Row],[Category]]="Footwear"),"High","Low") -> Low | O8: =TEXT(Table1[[#This Row],[Date]],"MMM-YY") -> Mar-25 | P8: =IF(Table1[[#This Row],[profit]]>5000000,"High",IF(Table1[[#This Row],[profit]]>3000000,"Medium","Low")) -> High | Q8: =IF(Table1[[#This Row],[Status]]="Completed","Paid","Notpaid") -> Paid
A9: ORD0008 | B9: 45718 | C9: Smartphone | D9: Electronics | E9: 3000 | F9: 23 | G9: =Table1[[#This Row],[Price]]*Table1[[#This Row],[Quantity]] -> 69000 | H9: Sophia Miller | I9: Miami | J9: PayPal | K9: Completed | L9: =Table1[[#This Row],[Total Sales]]*Table1[[#This Row],[Quantity]] -> 1587000 | N9: =IF(AND(Table1[[#This Row],[Price]]>50,Table1[[#This Row],[Category]]="Footwear"),"High","Low") -> Low | O9: =TEXT(Table1[[#This Row],[Date]],"MMM-YY") -> Mar-25 | P9: =IF(Table1[[#This Row],[profit]]>5000000,"High",IF(Table1[[#This Row],[profit]]>3000000,"Medium","Low")) -> Low | Q9: =IF(OR(Table1[[#This Row],[Status]]="Completed",Table1[[#This Row],[Status]]="Pending"),"Paid","Notpaid") -> Paid
A10: ORD0009 | B10: 45724 | C10: T-Shirt | D10: Clothing | E10: 5000 | F10: 89 | G10: =Table1[[#This Row],[Price]]*Table1[[#This Row],[Quantity]] -> 445000 | H10: Sophia Miller | I10: Boston | J10: PayPal | K10: Completed | L10: =Table1[[#This Row],[Total Sales]]*Table1[[#This Row],[Quantity]] -> 39605000 | N10: =IF(AND(Table1[[#This Row],[Price]]>50,Table1[[#This Row],[Category]]="Footwear"),"High","Low") -> Low | O10: =TEXT(Table1[[#This Row],[Date]],"MMM-YY") -> Mar-25 | P10: =IF(Table1[[#This Row],[profit]]>5000000,"High",IF(Table1[[#This Row],[profit]]>3000000,"Medium","Low")) -> High | Q10: =IF(OR(Table1[[#This Row],[Status]]="Completed",Table1[[#This Row],[Status]]="Pending"),"Paid","Notpaid") -> Paid
A11: ORD0010 | B11: 45728 | C11: Smartphone | D11: Electronics | E11: 2000 | F11: 42 | G11: =Table1[[#This Row],[Price]]*Table1[[#This Row],[Quantity]] -> 84000 | H11: Emily Johnson | I11: San Francisco | J11: Credit Card | K11: Pending | L11: =Table1[[#This Row],[Total Sales]]*Table1[[#This Row],[Quantity]] -> 3528000 | N11: =IF(AND(Table1[[#This Row],[Price]]>50,Table1[[#This Row],[Category]]="Footwear"),"High","Low") -> Low | O11: =TEXT(Table1[[#This Row],[Date]],"MMM-YY") -> Mar-25 | P11: =IF(Table1[[#This Row],[profit]]>5000000,"High",IF(Table1[[#This Row],[profit]]>3000000,"Medium","Low")) -> Medium | Q11: =IF(OR(Table1[[#This Row],[Status]]="Completed",Table1[[#This Row],[Status]]="Pending"),"Paid","Notpaid") -> Paid
A12: ORD0011 | B12: 45705 | C12: Book | D12: Books | E12: 2000 | F12: 51 | G12: =Table1[[#This Row],[Price]]*Table1[[#This Row],[Quantity]] -> 102000 | H12: David Lee | I12: Boston | J12: Amazon Pay | K12: Pending | L12: =Table1[[#This Row],[Total Sales]]*Table1[[#This Row],[Quantity]] -> 5202000 | N12: =IF(AND(Table1[[#This Row],[Price]]>50,Table1[[#This Row],[Category]]="Footwear"),"High","Low") -> Low | O12: =TEXT(Table1[[#This Row],[Date]],"MMM-YY") -> Feb-25 | P12: =IF(Table1[[#This Row],[profit]]>5000000,"High",IF(Table1[[#This Row],[profit]]>3000000,"Medium","Low")) -> High | Q12: =IF(OR(Table1[[#This Row],[Status]]="Completed",Table1[[#This Row],[Status]]="Pending"),"Paid","Notpaid") -> Paid
A13: ORD0012 | B13: 45729 | C13: Jeans | D13: Clothing | E13: 1000 | F13: 45 | G13: =Table1[[#This Row],[Price]]*Table1[[#This Row],[Quantity]] -> 45000 | H13: Michael Brown | I13: Dallas | J13: Credit Card | K13: Completed | L13: =Table1[[#This Row],[Total Sales]]*Table1[[#This Row],[Quantity]] -> 2025000 | N13: =IF(AND(Table1[[#This Row],[Price]]>50,Table1[[#This Row],[Category]]="Footwear"),"High","Low") -> Low | O13: =TEXT(Table1[[#This Row],[Date]],"MMM-YY") -> Mar-25 | P13: =IF(Table1[[#This Row],[profit]]>5000000,"High",IF(Table1[[#This Row],[profit]]>3000000,"Medium","Low")) -> Low | Q13: =IF(OR(Table1[[#This Row],[Status]]="Completed",Table1[[#This Row],[Status]]="Pending"),"Paid","Notpaid") -> Paid
A14: ORD0013 | B14: 45717 | C14: Laptop | D14: Electronics | E14: 500 | F14: 63 | G14: =Table1[[#This Row],[Price]]*Table1[[#This Row],[Quantity]] -> 31500 | H14: Daniel Harris | I14: San Francisco | J14: Gift Card | K14: Pending | L14: =Table1[[#This Row],[Total Sales]]*Table1[[#This Row],[Quantity]] -> 1984500 | N14: =IF(AND(Table1[[#This Row],[Price]]>50,Table1[[#This Row],[Category]]="Footwear"),"High","Low") -> Low | O14: =TEXT(Table1[[#This Row],[Date]],"MMM-YY") -> Mar-25 | P14: =IF(Table1[[#This Row],[profit]]>5000000,"High",IF(Table1[[#This Row],[profit]]>3000000,"Medium","Low")) -> Low | Q14: =IF(OR(Table1[[#This Row],[Status]]="Completed",Table1[[#This Row],[Status]]="Pending"),"Paid","no paid") -> Paid
A15: ORD0014 | B15: 45720 | C15: Washing Machine | D15: Home Appliances | E15: 2000 | F15: 35 | G15: =Table1[[#This Row],[Price]]*Table1[[#This Row],[Quantity]] -> 70000 | H15: Michael Brown | I15: Miami | J15: Credit Card | K15: Pending | L15: =Table1[[#This Row],[Total Sales]]*Table1[[#This Row],[Quantity]] -> 2450000 | N15: =IF(AND(Table1[[#This Row],[Price]]>50,Table1[[#This Row],[Category]]="Footwear"),"High","Low") -> Low | O15: =TEXT(Table1[[#This Row],[Date]],"MMM-YY") -> Mar-25 | P15: =IF(Table1[[#This Row],[profit]]>5000000,"High",IF(Table1[[#This Row],[profit]]>3000000,"Medium","Low")) -> Low | Q15: =IF(OR(Table1[[#This Row],[Status]]="Completed",Table1[[#This Row],[Status]]="Pending"),"Paid","no paid") -> Paid
A16: ORD0015 | B16: 45708 | C16: Smartwatch | D16: Electronics | E16: 3000 | F16: 44 | G16: =Table1[[#This Row],[Price]]*Table1[[#This Row],[Quantity]] -> 132000 | H16: John Doe | I16: Seattle | J16: Credit Card | K16: Completed | L16: =Table1[[#This Row],[Total Sales]]*Table1[[#This Row],[Quantity]] -> 5808000 | N16: =IF(AND(Table1[[#This Row],[Price]]>50,Table1[[#This Row],[Category]]="Footwear"),"High","Low") -> Low | O16: =TEXT(Table1[[#This Row],[Date]],"MMM-YY") -> Feb-25 | P16: =IF(Table1[[#This Row],[profit]]>5000000,"High",IF(Table1[[#This Row],[profit]]>3000000,"Medium","Low")) -> High | Q16: =IF(OR(Table1[[#This Row],[Status]]="Completed",Table1[[#This Row],[Status]]="Pending"),"Paid","no paid") -> Paid
A17: ORD0016 | B17: 45714 | C17: Refrigerator | D17: Home Appliances | E17: 5000 | F17: 22 | G17: =Table1[[#This Row],[Price]]*Table1[[#This Row],[Quantity]] -> 110000 | H17: John Doe | I17: Boston | J17: Credit Card | K17: Pending | L17: =Table1[[#This Row],[Total Sales]]*Table1[[#This Row],[Quantity]] -> 2420000 | N17: =IF(AND(Table1[[#This Row],[Price]]>50,Table1[[#This Row],[Category]]="Footwear"),"High","Low") -> Low | O17: =TEXT(Table1[[#This Row],[Date]],"MMM-YY") -> Feb-25 | P17: =IF(Table1[[#This Row],[profit]]>5000000,"High",IF(Table1[[#This Row],[profit]]>3000000,"Medium","Low")) -> Low | Q17: =IF(OR(Table1[[#This Row],[Status]]="Completed",Table1[[#This Row],[Status]]="Pending"),"Paid","no paid") -> Paid
A18: ORD0017 | B18: 45748 | C18: T-Shirt | D18: Clothing | E18: 2000 | F18: 16 | G18: =Table1[[#This Row],[Price]]*Table1[[#This Row],[Quantity]] -> 32000 | H18: Emma Clark | I18: New York | J18: Amazon Pay | K18: Completed | L18: =Table1[[#This Row],[Total Sales]]*Table1[[#This Row],[Quantity]] -> 512000 | N18: =IF(AND(Table1[[#This Row],[Price]]>50,Table1[[#This Row],[Category]]="Footwear"),"High","Low") -> Low | O18: =TEXT(Table1[[#This Row],[Date]],"MMM-YY") -> Apr-25 | P18: =IF(Table1[[#This Row],[profit]]>5000000,"High",IF(Table1[[#This Row],[profit]]>3000000,"Medium","Low")) -> Low | Q18: =IF(OR(Table1[[#This Row],[Status]]="Completed",Table1[[#This Row],[Status]]="Pending"),"Paid","no paid") -> Paid
A19: ORD0018 | B19: 45698 | C19: Smartphone | D19: Electronics | E19: 2000 | F19: 12 | G19: =Table1[[#This Row],[Price]]*Table1[[#This Row],[Quantity]] -> 24000 | H19: Michael Brown | I19: Los Angeles | J19: Amazon Pay | K19: Completed | L19: =Table1[[#This Row],[Total Sales]]*Table1[[#This Row],[Quantity]] -> 288000 | N19: =IF(AND(Table1[[#This Row],[Price]]>50,Table1[[#This Row],[Category]]="Footwear"),"High","Low") -> Low | O19: =TEXT(Table1[[#This Row],[Date]],"MMM-YY") -> Feb-25 | P19: =IF(Table1[[#This Row],[profit]]>5000000,"High",IF(Table1[[#This Row],[profit]]>3000000,"Medium","Low")) -> Low | Q19: =IF(OR(Table1[[#This Row],[Status]]="Completed",Table1[[#This Row],[Status]]="Pending"),"Paid","no paid") -> Paid
A20: ORD0019 | B20: 45738 | C20: Running Shoes | D20: Footwear | E20: 1000 | F20: 31 | G20: =Table1[[#This Row],[Price]]*Table1[[#This Row],[Quantity]] -> 31000 | H20: Olivia Wilson | I20: Houston | J20: Credit Card | K20: Completed | L20: =Table1[[#This Row],[Total Sales]]*Table1[[#This Row],[Quantity]] -> 961000 | N20: =IF(AND(Table1[[#This Row],[Price]]>50,Table1[[#This Row],[Category]]="Footwear"),"High","Low") -> High | O20: =TEXT(Table1[[#This Row],[Date]],"MMM-YY") -> Mar-25 | P20: =IF(Table1[[#This Row],[profit]]>5000000,"High",IF(Table1[[#This Row],[profit]]>3000000,"Medium","Low")) -> Low | Q20: =IF(OR(Table1[[#This Row],[Status]]="Completed",Table1[[#This Row],[Status]]="Pending"),"Paid","no paid") -> Paid
A21: ORD0020 | B21: 45723 | C21: Headphones | D21: Electronics | E21: 500 | F21: 63 | G21: =Table1[[#This Row],[Price]]*Table1[[#This Row],[Quantity]] -> 31500 | H21: Olivia Wilson | I21: Seattle | J21: Debit Card | K21: Pending | L21: =Table1[[#This Row],[Total Sales]]*Table1[[#This Row],[Quantity]] -> 1984500 | N21: =IF(AND(Table1[[#This Row],[Price]]>50,Table1[[#This Row],[Category]]="Footwear"),"High","Low") -> Low | O21: =TEXT(Table1[[#This Row],[Date]],"MMM-YY") -> Mar-25 | P21: =IF(Table1[[#This Row],[profit]]>5000000,"High",IF(Table1[[#This Row],[profit]]>3000000,"Medium","Low")) -> Low | Q21: =IF(OR(Table1[[#This Row],[Status]]="Completed",Table1[[#This Row],[Status]]="Pending"),"Paid","no paid") -> Paid
A22: ORD0021 | B22: 45693 | C22: Headphones | D22: Electronics | E22: 2000 | F22: 35 | G22: =Table1[[#This Row],[Price]]*Table1[[#This Row],[Quantity]] -> 70000 | H22: Chris White | I22: Miami | J22: Debit Card | K22: Completed | L22: =Table1[[#This Row],[Total Sales]]*Table1[[#This Row],[Quantity]] -> 2450000 | N22: =IF(AND(Table1[[#This Row],[Price]]>50,Table1[[#This Row],[Category]]="Footwear"),"High","Low") -> Low | O22: =TEXT(Table1[[#This Row],[Date]],"MMM-YY") -> Feb-25 | P22: =IF(Table1[[#This Row],[profit]]>5000000,"High",IF(Table1[[#This Row],[profit]]>3000000,"Medium","Low")) -> Low | Q22: =IF(OR(Table1[[#This Row],[Status]]="Completed",Table1[[#This Row],[Status]]="Pending"),"Paid","no paid") -> Paid
A23: ORD0022 | B23: 45723 | C23: Refrigerator | D23: Home Appliances | E23: 3000 | F23: 44 | G23: =Table1[[#This Row],[Price]]*Table1[[#This Row],[Quantity]] -> 132000 | H23: Olivia Wilson | I23: Houston | J23: Credit Card | K23: Pending | L23: =Table1[[#This Row],[Total Sales]]*Table1[[#This Row],[Quantity]] -> 5808000 | N23: =IF(AND(Table1[[#This Row],[Price]]>50,Table1[[#This Row],[Category]]="Footwear"),"High","Low") -> Low | O23: =TEXT(Table1[[#This Row],[Date]],"MMM-YY") -> Mar-25 | P23: =IF(Table1[[#This Row],[profit]]>5000000,"High",IF(Table1[[#This Row],[profit]]>3000000,"Medium","Low")) -> High | Q23: =IF(OR(Table1[[#This Row],[Status]]="Completed",Table1[[#This Row],[Status]]="Pending"),"Paid","no paid") -> Paid
A24: ORD0023 | B24: 45711 | C24: Book | D24: Books | E24: 5000 | F24: 22 | G24: =Table1[[#This Row],[Price]]*Table1[[#This Row],[Quantity]] -> 110000 | H24: Emma Clark | I24: Houston | J24: Credit Card | K24: Completed | L24: =Table1[[#This Row],[Total Sales]]*Table1[[#This Row],[Quantity]] -> 2420000 | N24: =IF(AND(Table1[[#This Row],[Price]]>50,Table1[[#This Row],[Category]]="Footwear"),"High","Low") -> Low | O24: =TEXT(Table1[[#This Row],[Date]],"MMM-YY") -> Feb-25 | P24: =IF(Table1[[#This Row],[profit]]>5000000,"High",IF(Table1[[#This Row],[profit]]>3000000,"Medium","Low")) -> Low | Q24: =IF(OR(Table1[[#This Row],[Status]]="Completed",Table1[[#This Row],[Status]]="Pending"),"Paid","no paid") -> Paid
A25: ORD0024 | B25: 45740 | C25: Refrigerator | D25: Home Appliances | E25: 2000 | F25: 16 | G25: =Table1[[#This Row],[Price]]*Table1[[#This Row],[Quantity]] -> 32000 | H25: Chris White | I25: Dallas | J25: Credit Card | K25: Pending | L25: =Table1[[#This Row],[Total Sales]]*Table1[[#This Row],[Quantity]] -> 512000 | N25: =IF(AND(Table1[[#This Row],[Price]]>50,Table1[[#This Row],[Category]]="Footwear"),"High","Low") -> Low | O25: =TEXT(Table1[[#This Row],[Date]],"MMM-YY") -> Mar-25 | P25: =IF(Table1[[#This Row],[profit]]>5000000,"High",IF(Table1[[#This Row],[profit]]>3000000,"Medium","Low")) -> Low | Q25: =IF(OR(Table1[[#This Row],[Status]]="Completed",Table1[[#This Row],[Status]]="Pending"),"Paid","no paid") -> Paid
... A251: ORD0250 | B251: 45707 | C251: Smartphone | D251: Electronics | E251: 8746 | F251: 4 | G251: =Table1[[#This Row],[Price]]*Table1[[#This Row],[Quantity]] -> 34984 | H251: Emily Johnson | I251: Seattle | J251: Amazon Pay | K251: Completed | L251: =Table1[[#This Row],[Total Sales]]*Table1[[#This Row],[Quantity]] -> 139936 | N251: =IF(AND(Table1[[#This Row],[Price]]>50,Table1[[#This Row],[Category]]="Footwear"),"High","Low") -> Low | O251: =TEXT(Table1[[#This Row],[Date]],"MMM-YY") -> Feb-25 | P251: =IF(Table1[[#This Row],[profit]]>5000000,"High",IF(Table1[[#This Row],[profit]]>3000000,"Medium","Low")) -> Low | Q251: =IF(OR(Table1[[#This Row],[Status]]="Completed",Table1[[#This Row],[Status]]="Pending"),"Paid","no paid") -> Paid

Sheet IF Condition
A1: customer loc | B1: high sales/low sales | C1: order month-year | D1: high/med/low profit | E1: paid/not paid
A2: =IF(Table1[[#This Row],[Customer Name]]="Emma Clark","EMMA CLARK",Table1[[#This Row],[Customer Name]]) -> EMMA CLARK | B2: =IF(AND(Table1[[#This Row],[Price]]>50,Table1[[#This Row],[Category]]="Footwear"),"High","Low") -> High | C2: =TEXT(Table1[[#This Row],[Date]],"MMM-YY") -> Mar-25 | D2: =IF(Table1[[#This Row],[profit]]>5000000,"High",IF(Table1[[#This Row],[profit]]>3000000,"Medium","Low")) -> Medium | E2: =IF(Table1[[#This Row],[Status]]="Completed","Paid","Not Paid") -> Paid
A3: =IF(Table1[[#This Row],[Customer Name]]="Emma Clark","EMMA CLARK",Table1[[#This Row],[Customer Name]]) -> Emily Johnson | B3: =IF(AND(Table1[[#This Row],[Price]]>50,Table1[[#This Row],[Category]]="Footwear"),"High","Low") -> Low | C3: =TEXT(Table1[[#This Row],[Date]],"MMM-YY") -> Mar-25 | D3: =IF(Table1[[#This Row],[profit]]>5000000,"High",IF(Table1[[#This Row],[profit]]>3000000,"Medium","Low")) -> High | E3: =IF(Table1[[#This Row],[Status]]="Completed","Paid","Not Paid") -> Not Paid
A4: =IF(Table1[[#This Row],[Customer Name]]="Emma Clark","EMMA CLARK",Table1[[#This Row],[Customer Name]]) -> John Doe | B4: =IF(AND(Table1[[#This Row],[Price]]>50,Table1[[#This Row],[Category]]="Footwear"),"High","Low") -> High | C4: =TEXT(Table1[[#This Row],[Date]],"MMM-YY") -> Feb-25 | D4: =IF(Table1[[#This Row],[profit]]>5000000,"High",IF(Table1[[#This Row],[profit]]>3000000,"Medium","Low")) -> High | E4: =IF(Table1[[#This Row],[Status]]="Completed","Paid","Not Paid") -> Paid
A5: =IF(Table1[[#This Row],[Customer Name]]="Emma Clark","EMMA CLARK",Table1[[#This Row],[Customer Name]]) -> Olivia Wilson | B5: =IF(AND(Table1[[#This Row],[Price]]>50,Table1[[#This Row],[Category]]="Footwear"),"High","Low") -> High | C5: =TEXT(Table1[[#This Row],[Date]],"MMM-YY") -> Feb-25 | D5: =IF(Table1[[#This Row],[profit]]>5000000,"High",IF(Table1[[#This Row],[profit]]>3000000,"Medium","Low")) -> High | E5: =IF(Table1[[#This Row],[Status]]="Completed","Paid","Not Paid") -> Not Paid
A6: =IF(Table1[[#This Row],[Customer Name]]="Emma Clark","EMMA CLARK",Table1[[#This Row],[Customer Name]]) -> EMMA CLARK | B6: =IF(AND(Table1[[#This Row],[Price]]>50,Table1[[#This Row],[Category]]="Footwear"),"High","Low") -> Low | C6: =TEXT(Table1[[#This Row],[Date]],"MMM-YY") -> Mar-25 | D6: =IF(Table1[[#This Row],[profit]]>5000000,"High",IF(Table1[[#This Row],[profit]]>3000000,"Medium","Low")) -> Low | E6: =IF(Table1[[#This Row],[Status]]="Completed","Paid","Not Paid") -> Not Paid
A7: =IF(Table1[[#This Row],[Customer Name]]="Emma Clark","EMMA CLARK",Table1[[#This Row],[Customer Name]]) -> John Doe | B7: =IF(AND(Table1[[#This Row],[Price]]>50,Table1[[#This Row],[Category]]="Footwear"),"High","Low") -> Low | C7: =TEXT(Table1[[#This Row],[Date]],"MMM-YY") -> Jan-00 | D7: =IF(Table1[[#This Row],[profit]]>5000000,"High",IF(Table1[[#This Row],[profit]]>3000000,"Medium","Low")) -> Low | E7: =IF(Table1[[#This Row],[Status]]="Completed","Paid","Not Paid") -> Not Paid
A8: =IF(Table1[[#This Row],[Customer Name]]="Emma Clark","EMMA CLARK",Table1[[#This Row],[Customer Name]]) -> EMMA CLARK | B8: =IF(AND(Table1[[#This Row],[Price]]>50,Table1[[#This Row],[Category]]="Footwear"),"High","Low") -> Low | C8: =TEXT(Table1[[#This Row],[Date]],"MMM-YY") -> Mar-25 | D8: =IF(Table1[[#This Row],[profit]]>5000000,"High",IF(Table1[[#This Row],[profit]]>3000000,"Medium","Low")) -> High | E8: =IF(Table1[[#This Row],[Status]]="Completed","Paid","Not Paid") -> Paid
A9: =IF(Table1[[#This Row],[Customer Name]]="Emma Clark","EMMA CLARK",Table1[[#This Row],[Customer Name]]) -> Sophia Miller | B9: =IF(AND(Table1[[#This Row],[Price]]>50,Table1[[#This Row],[Category]]="Footwear"),"High","Low") -> Low | C9: =TEXT(Table1[[#This Row],[Date]],"MMM-YY") -> Mar-25 | D9: =IF(Table1[[#This Row],[profit]]>5000000,"High",IF(Table1[[#This Row],[profit]]>3000000,"Medium","Low")) -> Low | E9: =IF(Table1[[#This Row],[Status]]="Completed","Paid","Not Paid") -> Paid
A10: =IF(Table1[[#This Row],[Customer Name]]="Emma Clark","EMMA CLARK",Table1[[#This Row],[Customer Name]]) -> Sophia Miller | B10: =IF(AND(Table1[[#This Row],[Price]]>50,Table1[[#This Row],[Category]]="Footwear"),"High","Low") -> Low | C10: =TEXT(Table1[[#This Row],[Date]],"MMM-YY") -> Mar-25 | D10: =IF(Table1[[#This Row],[profit]]>5000000,"High",IF(Table1[[#This Row],[profit]]>3000000,"Medium","Low")) -> High | E10: =IF(Table1[[#This Row],[Status]]="Completed","Paid","Not Paid") -> Paid
A11: =IF(Table1[[#This Row],[Customer Name]]="Emma Clark","EMMA CLARK",Table1[[#This Row],[Customer Name]]) -> Emily Johnson | B11: =IF(AND(Table1[[#This Row],[Price]]>50,Table1[[#This Row],[Category]]="Footwear"),"High","Low") -> Low | C11: =TEXT(Table1[[#This Row],[Date]],"MMM-YY") -> Mar-25 | D11: =IF(Table1[[#This Row],[profit]]>5000000,"High",IF(Table1[[#This Row],[profit]]>3000000,"Medium","Low")) -> Medium | E11: =IF(Table1[[#This Row],[Status]]="Completed","Paid","Not Paid") -> Not Paid
A12: =IF(Table1[[#This Row],[Customer Name]]="Emma Clark","EMMA CLARK",Table1[[#This Row],[Customer Name]]) -> David Lee | B12: =IF(AND(Table1[[#This Row],[Price]]>50,Table1[[#This Row],[Category]]="Footwear"),"High","Low") -> Low | C12: =TEXT(Table1[[#This Row],[Date]],"MMM-YY") -> Feb-25 | D12: =IF(Table1[[#This Row],[profit]]>5000000,"High",IF(Table1[[#This Row],[profit]]>3000000,"Medium","Low")) -> High | E12: =IF(Table1[[#This Row],[Status]]="Completed","Paid","Not Paid") -> Not Paid
A13: =IF(Table1[[#This Row],[Customer Name]]="Emma Clark","EMMA CLARK",Table1[[#This Row],[Customer Name]]) -> Michael Brown | B13: =IF(AND(Table1[[#This Row],[Price]]>50,Table1[[#This Row],[Category]]="Footwear"),"High","Low") -> Low | C13: =TEXT(Table1[[#This Row],[Date]],"MMM-YY") -> Mar-25 | D13: =IF(Table1[[#This Row],[profit]]>5000000,"High",IF(Table1[[#This Row],[profit]]>3000000,"Medium","Low")) -> Low | E13: =IF(Table1[[#This Row],[Status]]="Completed","Paid","Not Paid") -> Paid
... A251: =IF(Table1[[#This Row],[Customer Name]]="Emma Clark","EMMA CLARK",Table1[[#This Row],[Customer Name]]) -> Emily Johnson | B251: =IF(AND(Table1[[#This Row],[Price]]>50,Table1[[#This Row],[Category]]="Footwear"),"High","Low") -> Low | C251: =TEXT(Table1[[#This Row],[Date]],"MMM-YY") -> Feb-25 | D251: =IF(Table1[[#This Row],[profit]]>5000000,"High",IF(Table1[[#This Row],[profit]]>3000000,"Medium","Low")) -> Low | E251: =IF(Table1[[#This Row],[Status]]="Completed","Paid","Not Paid") -> Paid

Sheet amazon dashboard
